ailever/__init__.py
ailever/_authors.py
ailever/_typecore.py
ailever/_version_info.py
ailever/dashboard.py
ailever/docs.py
ailever/evaluations.py
ailever/helpers.py
ailever/logging_system.py
ailever/path.py
ailever/requirements.py
ailever/security.py
ailever/analysis/ANALYSISInterfaces.py
ailever/analysis/__init__.py
ailever/analysis/_base_policy.py
ailever/analysis/dashboard.py
ailever/analysis/data_preprocessing.py
ailever/analysis/data_processing.py
ailever/analysis/data_transformation.py
ailever/analysis/digitization_for_categorical_variables.py
ailever/analysis/evaluations.py
ailever/analysis/exploratory_data_analysis.py
ailever/analysis/hypothesis_testing.py
ailever/analysis/linearity_analysis.py
ailever/analysis/probability.py
ailever/analysis/time_series_preprocessing.py
ailever/analysis/uci_machine_learning_repository.py
ailever/analysis/accounting/ACCOUNTINGInterfaces.py
ailever/analysis/accounting/__init__.py
ailever/analysis/accounting/dashboard.py
ailever/analysis/banking/BANKINGInterfaces.py
ailever/analysis/banking/__init__.py
ailever/analysis/banking/interest_rate.py
ailever/analysis/chemistry/CHEMISTRYInterfaces.py
ailever/analysis/chemistry/__init__.py
ailever/analysis/chemistry/dashboard.py
ailever/analysis/economics/ECONOMICSInterfaces.py
ailever/analysis/economics/__init__.py
ailever/analysis/economics/dashboard.py
ailever/analysis/finance/FINANCEInterfaces.py
ailever/analysis/finance/__init__.py
ailever/analysis/finance/_arbitrage.py
ailever/analysis/finance/_capital_asset.py
ailever/analysis/finance/_influence_diagram.py
ailever/analysis/finance/_kr_financial_statements.py
ailever/analysis/finance/_option.py
ailever/analysis/finance/_portfolio.py
ailever/analysis/finance/dashboard.py
ailever/analysis/finance/interest_rate.py
ailever/analysis/insurance/INSURANCEInteraces.py
ailever/analysis/insurance/__init__.py
ailever/analysis/physics/PHYSICSManagement.py
ailever/analysis/physics/__init__.py
ailever/analysis/physics/_equation_newton.py
ailever-1.0.120.dist-info/METADATA
ailever-1.0.120.dist-info/WHEEL
ailever-1.0.120.dist-info/top_level.txt
ailever-1.0.120.dist-info/RECORD
