Metadata-Version: 2.1
Name: ailever
Version: 1.0.120
Summary: Clever Artificial Intelligence
Home-page: https://gitlab.com/aileverlabs/ailever
Author: ailever
Author-email: gitlab@aileverlabs.com
License: UNKNOWN
Keywords: ailever,clever,artificial intelligence
Platform: UNKNOWN
Classifier: Programming Language :: Python :: 3.6
Classifier: Programming Language :: Python :: 3.7
Classifier: Programming Language :: Python :: 3.8
Classifier: Programming Language :: Python :: 3.9
Classifier: Programming Language :: Python :: 3.10
Requires-Python: >=3
Requires-Dist: dash
Requires-Dist: dash-bootstrap-components
Requires-Dist: plotly
Requires-Dist: beautifulsoup4
Requires-Dist: yahooquery
Requires-Dist: finance-datareader
Requires-Dist: statsmodels
Requires-Dist: seaborn
Requires-Dist: matplotlib
Requires-Dist: pandas
Requires-Dist: numpy
Requires-Dist: requests
